CHANGELOG.md
cagu_toolkit/__init__.py
cagu_toolkit/cli.py
cagu_toolkit/commands/__init__.py
cagu_toolkit/commands/config.py
cagu_toolkit/commands/gpt.py
cagu_toolkit/commands/import_data.py
cagu_toolkit/common/__init__.py
cagu_toolkit/common/config.py
cagu_toolkit/common/config_manager.py
cagu_toolkit/common/context.py
cagu_toolkit/common/db_manager.py
cagu_toolkit/common/exceptions.py
cagu_toolkit/common/logging_config.py
cagu_toolkit/common/utils.py
cagu_toolkit/modal/__init__.py
cagu_toolkit/modal/category.py
cagu_toolkit/modal/enum_type_decorator.py
cagu_toolkit/modal/exchange_rate.py
cagu_toolkit/modal/logistics_channel.py
cagu_toolkit/modal/product.py
cagu_toolkit/modal/sku.py
cagu_toolkit/modal/sku_freight_estimation.py
cagu_toolkit/modal/supplier.py
cagu_toolkit/service/__init__.py
cagu_toolkit/service/data_importer.py
cagu_toolkit/service/gpt.py
cagu_toolkit/service/version.py
cagu_toolkit-0.1.11.dist-info/METADATA
cagu_toolkit-0.1.11.dist-info/WHEEL
cagu_toolkit-0.1.11.dist-info/entry_points.txt
cagu_toolkit-0.1.11.dist-info/RECORD
