Metadata-Version: 2.1
Name: cagu-toolkit
Version: 0.1.11
Summary: 卡谷电商的工具集合
License: MIT
Author: gongxunyao
Author-email: eric.gong@caguuu.com
Requires-Python: >=3.6,<4.0
Classifier: License :: OSI Approved :: MIT License
Classifier: Operating System :: OS Independent
Classifier: Programming Language :: Python :: 3
Classifier: Programming Language :: Python :: 3.6
Classifier: Programming Language :: Python :: 3.7
Classifier: Programming Language :: Python :: 3.8
Classifier: Programming Language :: Python :: 3.9
Classifier: Programming Language :: Python :: 3.10
Classifier: Programming Language :: Python :: 3.11
Classifier: Programming Language :: Python :: 3.12
Classifier: Programming Language :: Python :: 3.13
Requires-Dist: SQLAlchemy (==2.0.36)
Requires-Dist: click (==8.1.8)
Requires-Dist: openai (==1.58.1)
Requires-Dist: openpyxl (>=3.1.5,<4.0.0)
Requires-Dist: pandas (==2.2.3)
Requires-Dist: pydantic-settings (>=2.7.0,<3.0.0)
Requires-Dist: pymysql (>=1.1.1,<2.0.0)
Requires-Dist: python_dateutil (==2.9.0.post0)
Requires-Dist: requests (>=2.32.3,<3.0.0)
Requires-Dist: tabulate (==0.9.0)
Requires-Dist: tqdm (==4.67.1)
